__init__.py
FUNCTIONS/functions.py
wbasics-0.0.1.dist-info/METADATA
wbasics-0.0.1.dist-info/WHEEL
wbasics-0.0.1.dist-info/licenses/LICENSE
wbasics-0.0.1.dist-info/RECORD
