Metadata-Version: 2.1
Name: Wbasics
Version: 0.0.1
Summary: Wbasics
Project-URL: Homepage, https://github.com/Wesleyplayz08/Wbasics-API
Project-URL: Bug Tracker, https://github.com/Wesleyplayz08/Wbasics-API/issues
Author-email: wesleyplayz08 <whohmann4@gmail.com>
License-File: LICENSE
Classifier: License :: OSI Approved :: GNU General Public License v3 (GPLv3)
Classifier: Operating System :: OS Independent
Classifier: Programming Language :: Python :: 3
Requires-Python: >=3.7
